pyfb_routing/__init__.py
pyfb_routing/admin.py
pyfb_routing/api.py
pyfb_routing/apps.py
pyfb_routing/forms.py
pyfb_routing/models.py
pyfb_routing/serializers.py
pyfb_routing/urls.py
pyfb_routing/views.py
pyfb_routing/migrations/0001_initial.py
pyfb_routing/migrations/0002_auto_20181221_1409.py
pyfb_routing/migrations/__init__.py
pyfb_routing/static/css/pyfb_routing.css
pyfb_routing/static/js/pyfb_routing.js
pyfb_routing/templates/pyfb_routing/countryrule_detail.html
pyfb_routing/templates/pyfb_routing/countryrule_form.html
pyfb_routing/templates/pyfb_routing/countryrule_list.html
pyfb_routing/templates/pyfb_routing/countrytyperule_detail.html
pyfb_routing/templates/pyfb_routing/countrytyperule_form.html
pyfb_routing/templates/pyfb_routing/countrytyperule_list.html
pyfb_routing/templates/pyfb_routing/customerroutinggroup_detail.html
pyfb_routing/templates/pyfb_routing/customerroutinggroup_form.html
pyfb_routing/templates/pyfb_routing/customerroutinggroup_list.html
pyfb_routing/templates/pyfb_routing/defaultrule_detail.html
pyfb_routing/templates/pyfb_routing/defaultrule_form.html
pyfb_routing/templates/pyfb_routing/defaultrule_list.html
pyfb_routing/templates/pyfb_routing/destinationrule_detail.html
pyfb_routing/templates/pyfb_routing/destinationrule_form.html
pyfb_routing/templates/pyfb_routing/destinationrule_list.html
pyfb_routing/templates/pyfb_routing/prefixrule_detail.html
pyfb_routing/templates/pyfb_routing/prefixrule_form.html
pyfb_routing/templates/pyfb_routing/prefixrule_list.html
pyfb_routing/templates/pyfb_routing/regionrule_detail.html
pyfb_routing/templates/pyfb_routing/regionrule_form.html
pyfb_routing/templates/pyfb_routing/regionrule_list.html
pyfb_routing/templates/pyfb_routing/regiontyperule_detail.html
pyfb_routing/templates/pyfb_routing/regiontyperule_form.html
pyfb_routing/templates/pyfb_routing/regiontyperule_list.html
pyfb_routing/templates/pyfb_routing/routinggroup_detail.html
pyfb_routing/templates/pyfb_routing/routinggroup_form.html
pyfb_routing-1.0.1.dist-info/AUTHORS.rst
pyfb_routing-1.0.1.dist-info/LICENSE
pyfb_routing-1.0.1.dist-info/METADATA
pyfb_routing-1.0.1.dist-info/WHEEL
pyfb_routing-1.0.1.dist-info/top_level.txt
pyfb_routing-1.0.1.dist-info/RECORD
