Metadata-Version: 2.1
Name: pyfb-routing
Version: 1.0.1
Summary: Routing package for PyFreeBilling application
Home-page: https://www.pyfreebilling.com
Author: Mathias WOLFF
Author-email: mathias@celea.org
License: MIT
Keywords: pyfb-routing
Platform: UNKNOWN
Classifier: Development Status :: 5 - Production/Stable
Classifier: Framework :: Django :: 2.2
Classifier: Intended Audience :: Developers
Classifier: License :: OSI Approved :: MIT License
Classifier: Natural Language :: English
Classifier: Programming Language :: Python :: 3.5
Classifier: Programming Language :: Python :: 3.6
Requires-Dist: django-model-utils (>=2.0)
Requires-Dist: django-extensions (>=2.1.3)
Requires-Dist: djangorestframework (>=3.7.7)
Requires-Dist: django-crispy-forms (>=1.7.0)
Requires-Dist: pyfb-direction (>=0.9.0)
Requires-Dist: pyfb-endpoint (>=0.9.1)
Requires-Dist: pyfb-rating (>=0.11.0)
Requires-Dist: django-partial-index (>=0.5.2)
